ai_providers_and_models/__init__.py
ai_providers_and_models/models.py
ai_providers_and_models/providers_file.py
ai_providers_and_models/data/models.yaml
ai_providers_and_models-0.1.13.dist-info/METADATA
ai_providers_and_models-0.1.13.dist-info/WHEEL
ai_providers_and_models-0.1.13.dist-info/top_level.txt
ai_providers_and_models-0.1.13.dist-info/RECORD
