Metadata-Version: 2.4
Name: ai_providers_and_models
Version: 0.1.13
Summary: AI providers and models data module for Python
Requires-Python: >=3.8
Requires-Dist: PyYAML>=6.0
Requires-Dist: pydantic>=1.8
